automatoes/__init__.py
automatoes/acme.py
automatoes/authorize.py
automatoes/crypto.py
automatoes/errors.py
automatoes/helpers.py
automatoes/info.py
automatoes/issue.py
automatoes/messages.py
automatoes/migrate.py
automatoes/model.py
automatoes/protocol.py
automatoes/register.py
automatoes/revoke.py
automatoes/upgrade.py
automatoes/bin/__init__.py
automatoes/bin/automatoes-cli.py
automatoes/bin/manuale-cli.py
automatoes/cli/__init__.py
automatoes/cli/automatoes.py
automatoes/cli/manuale.py
automatoes/cli/commands/__init__.py
automatoes/cli/commands/account.py
automatoes/cli/commands/help.py
automatoes/cli/commands/order.py
automatoes/conf/automatoes.yml
automatoes/conf/manuale.yml
automatoes-0.9.14.dist-info/licenses/LICENSE
tests/__init__.py
tests/ari_test.py
tests/crypto_test.py
tests/nonce_test.py
tests/runintegrationtests.py
tests/runtests.py
tests/user_management_test.py
tests/features/__init__.py
tests/features/environment.py
automatoes-0.9.14.dist-info/METADATA
automatoes-0.9.14.dist-info/WHEEL
automatoes-0.9.14.dist-info/entry_points.txt
automatoes-0.9.14.dist-info/top_level.txt
automatoes-0.9.14.dist-info/RECORD
