Metadata-Version: 2.4
Name: automatoes
Version: 0.9.14
Summary: Let's Encrypt/ACME V2 client replacement for Manuale. Manual or automated your choice.
Home-page: https://github.com/candango/automatoes
Author: Flavio Garcia
Author-email: piraz@candango.org
License: Apache License V2.0
Classifier: Development Status :: 5 - Production/Stable
Classifier: License :: OSI Approved :: Apache Software License
Classifier: Environment :: Console
Classifier: Environment :: Web Environment
Classifier: Intended Audience :: Developers
Classifier: Intended Audience :: System Administrators
Classifier: Programming Language :: Python :: 3
Classifier: Programming Language :: Python :: 3.9
Classifier: Programming Language :: Python :: 3.10
Classifier: Programming Language :: Python :: 3.11
Classifier: Programming Language :: Python :: 3.12
Classifier: Programming Language :: Python :: 3.13
Classifier: Programming Language :: Python :: 3 :: Only
Requires-Python: >= 3.9
License-File: LICENSE
Requires-Dist: peasant[requests]>=0.7.5
Requires-Dist: taskio>=0.0.7
Dynamic: author
Dynamic: author-email
Dynamic: classifier
Dynamic: description
Dynamic: description-content-type
Dynamic: home-page
Dynamic: license
Dynamic: license-file
Dynamic: requires-dist
Dynamic: requires-python
Dynamic: summary
